strategic_ml/__init__.py
strategic_ml/cost_functions/__init__.py
strategic_ml/cost_functions/cost_function.py
strategic_ml/cost_functions/norms.py
strategic_ml/gsc/__init__.py
strategic_ml/gsc/generalized_strategic_delta.py
strategic_ml/gsc/identity_delta.py
strategic_ml/gsc/linear_gp/__init__.py
strategic_ml/gsc/linear_gp/linear_adv_delta.py
strategic_ml/gsc/linear_gp/linear_gp.py
strategic_ml/gsc/linear_gp/linear_strategic_delta.py
strategic_ml/gsc/non_linear_gp/__init__.py
strategic_ml/gsc/non_linear_gp/non_linear_adv_delta.py
strategic_ml/gsc/non_linear_gp/non_linear_gp.py
strategic_ml/gsc/non_linear_gp/non_linear_strategic_delta.py
strategic_ml/loss_functions/__init__.py
strategic_ml/loss_functions/strategic_hinge_loss.py
strategic_ml/model_suit/__init__.py
strategic_ml/model_suit/model_suit.py
strategic_ml/models/__init__.py
strategic_ml/models/linear_model.py
strategic_ml/models/linear_regularization.py
strategic_ml/regularization/__init__.py
strategic_ml/regularization/expected_utility.py
strategic_ml/regularization/recourse.py
strategic_ml/regularization/social_burden.py
strategic_ml/regularization/strategic_regularization.py
strategic_ml/utils/__init__.py
strategic_ml/utils/visualize_utils.py
strategic_ml-0.1.0.dist-info/LICENSE
strategic_ml-0.1.0.dist-info/METADATA
strategic_ml-0.1.0.dist-info/WHEEL
strategic_ml-0.1.0.dist-info/top_level.txt
strategic_ml-0.1.0.dist-info/RECORD
