Metadata-Version: 2.1
Name: strategic-ml
Version: 0.1.0
Summary: A comprehensive library for strategic machine learning models
Home-page: https://github.com/orimintz21/strategic_ml
Author: Your Name
Author-email: orimintz21@gmail.com
Project-URL: Documentation, https://github.com/orimintz21/strategic_ml#readme
Project-URL: Source Code, https://github.com/orimintz21/strategic_ml
Project-URL: Bug Tracker, https://github.com/orimintz21/strategic_ml/issues
Classifier: Development Status :: 4 - Beta
Classifier: Intended Audience :: Developers
Classifier: Topic :: Scientific/Engineering :: Artificial Intelligence
Classifier: Programming Language :: Python :: 3
Classifier: Programming Language :: Python :: 3.8
Classifier: License :: OSI Approved :: MIT License
Classifier: Operating System :: OS Independent
Requires-Python: >=3.6
License-File: LICENSE
Requires-Dist: torch>=2.1.0
Requires-Dist: pytorch-lightning>=2
Requires-Dist: numpy>=1.19.0
